main.py
obsidianki_mcp-0.1.1.dist-info/METADATA
obsidianki_mcp-0.1.1.dist-info/WHEEL
obsidianki_mcp-0.1.1.dist-info/entry_points.txt
obsidianki_mcp-0.1.1.dist-info/top_level.txt
obsidianki_mcp-0.1.1.dist-info/RECORD
