Metadata-Version: 2.4
Name: obsidianki-mcp
Version: 0.1.1
Summary: MCP server for generating flashcards using obsidianki
Author-email: ccmdi <ccmdi.dev@gmail.com>
License: MIT
Project-URL: Homepage, https://github.com/ccmdi/obsidianki-mcp
Project-URL: Repository, https://github.com/ccmdi/obsidianki-mcp
Project-URL: Issues, https://github.com/ccmdi/obsidianki-mcp/issues
Keywords: mcp,obsidian,anki,flashcards,spaced-repetition
Classifier: Development Status :: 3 - Alpha
Classifier: Intended Audience :: Developers
Classifier: Topic :: Education
Classifier: License :: OSI Approved :: MIT License
Classifier: Programming Language :: Python :: 3
Classifier: Programming Language :: Python :: 3.11
Requires-Python: >=3.11
Requires-Dist: mcp[cli]>=1.16.0
